odoo/addons/sale_loyalty_partner/README.rst
odoo/addons/sale_loyalty_partner/__init__.py
odoo/addons/sale_loyalty_partner/__manifest__.py
odoo/addons/sale_loyalty_partner/i18n/it.po
odoo/addons/sale_loyalty_partner/i18n/sale_loyalty_partner.pot
odoo/addons/sale_loyalty_partner/models/__init__.py
odoo/addons/sale_loyalty_partner/models/loyalty_program.py
odoo/addons/sale_loyalty_partner/readme/CONTEXT.md
odoo/addons/sale_loyalty_partner/readme/CONTRIBUTORS.md
odoo/addons/sale_loyalty_partner/readme/DESCRIPTION.md
odoo/addons/sale_loyalty_partner/reports/__init__.py
odoo/addons/sale_loyalty_partner/reports/sale_report.py
odoo/addons/sale_loyalty_partner/reports/sale_report_views.xml
odoo/addons/sale_loyalty_partner/static/description/icon.png
odoo/addons/sale_loyalty_partner/static/description/index.html
odoo/addons/sale_loyalty_partner/tests/__init__.py
odoo/addons/sale_loyalty_partner/tests/test_sale_loyalty_loyalty_program.py
odoo/addons/sale_loyalty_partner/views/sale_loyalty_program_views.xml
odoo_addon_sale_loyalty_partner-18.0.1.0.0.2.dist-info/METADATA
odoo_addon_sale_loyalty_partner-18.0.1.0.0.2.dist-info/WHEEL
odoo_addon_sale_loyalty_partner-18.0.1.0.0.2.dist-info/top_level.txt
odoo_addon_sale_loyalty_partner-18.0.1.0.0.2.dist-info/RECORD
